edatool/__init__.py
edatool/main.py
EDAtool-0.0.1.dist-info/LICENSE
EDAtool-0.0.1.dist-info/METADATA
EDAtool-0.0.1.dist-info/WHEEL
EDAtool-0.0.1.dist-info/top_level.txt
EDAtool-0.0.1.dist-info/RECORD
