Metadata-Version: 2.1
Name: EDAtool
Version: 0.0.1
Summary: EDA_TOOL
Home-page: UNKNOWN
Author: Ketto
Author-email: analytics@ketto.org
License: MIT License
Platform: UNKNOWN
Classifier: Development Status :: 1 - Planning
Classifier: Intended Audience :: Developers
Classifier: Programming Language :: Python :: 3
Classifier: Operating System :: Unix
Classifier: Operating System :: MacOS :: MacOS X
Classifier: Operating System :: Microsoft :: Windows
License-File: LICENSE
Requires-Dist: streamlit
